{
  "venues": [
    "桐生", "戸田", "江戸川", "平和島", "多摩川", "浜名湖",
    "蒲郡", "常滑", "津", "三国", "びわこ", "住之江",
    "尼崎", "鳴門", "丸亀", "児島", "宮島", "徳山",
    "下関", "若松", "芦屋", "唐津", "大村", "福岡"
  ],
  "races": [
    {
      "venue": "桐生",
      "race_number": 1,
      "entries": [
        { "name": "選手A", "mark": "◎" },
        { "name": "選手B", "mark": "○" },
        { "name": "選手C", "mark": "▲" },
        { "name": "選手D", "mark": "△" },
        { "name": "選手E", "mark": "-" },
        { "name": "選手F", "mark": "-" }
      ],
      "predictions": [
        { "bet": "1-2-3", "percent": 45 },
        { "bet": "1-3-2", "percent": 25 },
        { "bet": "2-1-3", "percent": 15 },
        { "bet": "3-1-2", "percent": 15 }
      ]
    }
  ]
}